CHANGES.rst
CONTRIBUTORS.rst
MANIFEST.in
README.rst
setup.cfg
setup.py
docs/LICENSE.GPL
docs/LICENSE.rst
docs/index.rst
src/experimental/__init__.py
src/experimental.nodtml.egg-info/PKG-INFO
src/experimental.nodtml.egg-info/SOURCES.txt
src/experimental.nodtml.egg-info/dependency_links.txt
src/experimental.nodtml.egg-info/entry_points.txt
src/experimental.nodtml.egg-info/namespace_packages.txt
src/experimental.nodtml.egg-info/not-zip-safe
src/experimental.nodtml.egg-info/requires.txt
src/experimental.nodtml.egg-info/top_level.txt
src/experimental/nodtml/__init__.py
src/experimental/nodtml/tests.py