Metadata-Version: 1.1
Name: experimental.nodtml
Version: 1.2
Summary: Patch DocumentTemplate to not return any content.
Home-page: https://pypi.python.org/pypi/experimental.nodtml
Author: Maurits van Rees
Author-email: maurits@vanrees.org
License: GPL version 2
Keywords: Python Plone
Platform: UNKNOWN
Classifier: Environment :: Web Environment
Classifier: Framework :: Plone
Classifier: Framework :: Plone :: 4.3
Classifier: Framework :: Plone :: 5.0
Classifier: Framework :: Plone :: 5.1
Classifier: Programming Language :: Python
Classifier: Programming Language :: Python :: 2.6
Classifier: Programming Language :: Python :: 2.7
Classifier: Operating System :: OS Independent
Classifier: License :: OSI Approved :: GNU General Public License v2 (GPLv2)
